py3_images/__init__.py
py3_images/imgkit/__init__.py
py3_images-1.0.1.dist-info/LICENSE
py3_images-1.0.1.dist-info/METADATA
py3_images-1.0.1.dist-info/WHEEL
py3_images-1.0.1.dist-info/top_level.txt
py3_images-1.0.1.dist-info/RECORD
