Metadata-Version: 2.1
Name: py3-images
Version: 1.0.1
Summary: The Python3 Images Library Developed By Guolei
Home-page: https://github.com/guolei19850528/py3_images
Author: guolei
Author-email: 174000902@qq.com
License: MIT
Requires-Python: >=3.0
License-File: LICENSE
Requires-Dist: py3-requests
Requires-Dist: addict
Requires-Dist: retrying
Requires-Dist: jsonschema
Requires-Dist: imgkit
Requires-Dist: Pillow
Requires-Dist: setuptools
Requires-Dist: wheel
